dir2prompt-2.0.9.dist-info/METADATA
dir2prompt-2.0.9.dist-info/WHEEL
dir2prompt-2.0.9.dist-info/entry_points.txt
dir2prompt-2.0.9.dist-info/licenses/LICENSE
dir2prompt/__init__.py
dir2prompt/dir2prompt.cpython-39-darwin.so
dir2prompt-2.0.9.dist-info/RECORD
