Metadata-Version: 2.4
Name: dir2prompt
Version: 2.0.9
Classifier: Development Status :: 3 - Alpha
Classifier: Intended Audience :: Developers
Classifier: License :: OSI Approved :: MIT License
License-File: LICENSE
Summary: Generate prompts for long-context LLMs using the content in your directory
Keywords: prompt engineering,large language model,directory structure,prompt generation,file tree visualization,directory to prompt,automation tools,developer utilities,code documentation
Author-email: Max Kieffer <wkieffer@ufl.edu>
Requires-Python: >=3.6
Project-URL: Homepage, https://github.com/mkieffer1107/dir2prompt
Project-URL: Issues, https://github.com/mkieffer1107/dir2prompt/issues
